graphxplore/__init__.py
graphxplore/Basis/__init__.py
graphxplore/Basis/graph_classes.py
graphxplore/Basis/graph_io_handlers.py
graphxplore/Basis/utils.py
graphxplore/Basis/AttributeAssociationGraph/__init__.py
graphxplore/Basis/AttributeAssociationGraph/attribute_association_graph_classes.py
graphxplore/Basis/BaseGraph/__init__.py
graphxplore/Basis/BaseGraph/base_classes.py
graphxplore/Dashboard/__init__.py
graphxplore/Dashboard/dashboard_buider.py
graphxplore/Dashboard/meta_distribution_plotter.py
graphxplore/DataMapping/__init__.py
graphxplore/DataMapping/data_aggregator.py
graphxplore/DataMapping/data_mapping.py
graphxplore/DataMapping/data_structure_transformer.py
graphxplore/DataMapping/data_transformation.py
graphxplore/DataMapping/mapping_utils.py
graphxplore/DataMapping/meta_lattice.py
graphxplore/DataMapping/variable_mapping.py
graphxplore/DataMapping/Conclusions/__init__.py
graphxplore/DataMapping/Conclusions/conclusions.py
graphxplore/DataMapping/Conditionals/__init__.py
graphxplore/DataMapping/Conditionals/logic_operators.py
graphxplore/GraphDataScience/__init__.py
graphxplore/GraphDataScience/attribute_association_graph_generator.py
graphxplore/GraphDataScience/group_selector.py
graphxplore/GraphDataScience/post_filter.py
graphxplore/GraphDataScience/pre_filter.py
graphxplore/GraphTranslation/__init__.py
graphxplore/GraphTranslation/graph_translator.py
graphxplore/MetaDataHandling/__init__.py
graphxplore/MetaDataHandling/meta_data.py
graphxplore/MetaDataHandling/meta_data_generator.py
graphxplore/MetaDataHandling/variable_info.py
graphxplore-1.0.1.dist-info/LICENSE
graphxplore-1.0.1.dist-info/METADATA
graphxplore-1.0.1.dist-info/WHEEL
graphxplore-1.0.1.dist-info/top_level.txt
graphxplore-1.0.1.dist-info/RECORD
