Metadata-Version: 2.1
Name: graphxplore
Version: 1.0.1
Summary: data exploration using graph representations and dashboards, as well as meta data extraction, cleaning, and transformation
Author: Louis Bellmann
License: Copyright 2024 Medical Center Hamburg-Eppendorf and Louis Bellmann
Project-URL: Homepage, https://github.com/UKEIAM/graphxplore
Project-URL: Documentation, https://graphxplore.readthedocs.io/en/latest/
Project-URL: User Guide, https://ukeiam.github.io/graphxplore/
Classifier: Programming Language :: Python :: 3
Classifier: License :: OSI Approved :: MIT License
Classifier: Operating System :: OS Independent
Requires-Python: >=3.10
License-File: LICENSE
Requires-Dist: neo4j ==5.25.0
Requires-Dist: chardet ==5.2.0
Requires-Dist: plotly ==5.24.1
Requires-Dist: pandas ==2.2.3
